{
  "cursistas": [
    { "login": "6386351", "senha": "Sgp@1234" },
    { "login": "6809472", "senha": "Sgp@1234" },
    { "login": "6944060", "senha": "Sgp@1234" },
    { "login": "6991637", "senha": "Sgp@1234" },
    { "login": "7184140", "senha": "Sgp@1234" },
    { "login": "6956157", "senha": "Sgp@1234" },
    { "login": "7453671", "senha": "Sgp@1234" },
    { "login": "7387741", "senha": "Sgp@1234" },
    { "login": "6769195", "senha": "Sgp@1234" },

    { "login": "1168991", "senha": "Sgp@1234" },
    { "login": "07330509213", "senha": "Sgp@1234" },
    { "login": "1346784", "senha": "Sgp@1234" },
    { "login": "1398717", "senha": "Sgp@1234" },
    { "login": "6907822", "senha": "Sgp@1234" },
    { "login": "7285388", "senha": "Sgp@1234" },
    { "login": "7907770", "senha": "Sgp@1234" }
  ],
  "admin": {
    "login": "6809472",
    "senha": "Sgp@1234"
  }
}